http_test/__init__.py
http_test/request.py
http_test/runner.py
http_test/spec.py
http_test/ws_request.py
py_http_auto_test-1.0.20.data/scripts/http-test-runner.py
py_http_auto_test-1.0.20.dist-info/METADATA
py_http_auto_test-1.0.20.dist-info/WHEEL
py_http_auto_test-1.0.20.dist-info/top_level.txt
py_http_auto_test-1.0.20.dist-info/RECORD
