Metadata-Version: 2.1
Name: py-http-auto-test
Version: 1.0.20
Summary: Python HTTP automated testing facility
Home-page: https://github.com/cosimo/py-http-auto-test
Author: Cosimo Streppone
Author-email: cosimo@streppone.it
License: MIT
Classifier: Development Status :: 4 - Beta
Classifier: Environment :: Console
Classifier: License :: OSI Approved :: MIT License
Classifier: Topic :: Utilities
Classifier: Operating System :: OS Independent
Requires-Python: >=3.8
Requires-Dist: pytest~=7.4
Requires-Dist: pycurl~=7.45.2
Requires-Dist: brotli==1.0.9
Requires-Dist: certifi~=2023.7.22
Requires-Dist: asyncio==3.4.3
Requires-Dist: websockets~=13.1.0
Requires-Dist: pyyaml
Requires-Dist: jinja2~=3.1.2
Requires-Dist: click~=8.1.7
Requires-Dist: setuptools~=68.0.0
